DeepDrishti/__init__.py
DeepDrishti/models/__init__.py
DeepDrishti/models/faster_rcnn/__init__.py
DeepDrishti/models/faster_rcnn/dataloader.py
DeepDrishti/models/faster_rcnn/model.py
DeepDrishti/models/faster_rcnn/utils.py
DeepDrishti/utils/__init__.py
DeepDrishti/utils/yaml.py
DeepDrishti-0.0.5.dist-info/METADATA
DeepDrishti-0.0.5.dist-info/WHEEL
DeepDrishti-0.0.5.dist-info/top_level.txt
DeepDrishti-0.0.5.dist-info/RECORD
