Metadata-Version: 2.1
Name: DeepDrishti
Version: 0.0.5
Summary: A set of python modules for Computer Vision
Home-page: https://github.com/playatanu/DeepDrishti
Author: Atanu Debnath
Author-email: playatanu@gmail.com
License: MIT
Project-URL: Documentation, https://playatanu.github.io/DeepDrishti
Project-URL: Source, https://github.com/playatanu/DeepDrishti
Project-URL: Tracker, https://github.com/playatanu/DeepDrishti/issues
Classifier: Programming Language :: Python :: 3
Classifier: License :: OSI Approved :: MIT License
Requires-Python: >=3.10
Requires-Dist: pillow
Requires-Dist: numpy
Requires-Dist: torch
Requires-Dist: torchvision
Requires-Dist: tqdm
